{
    "totalcount": 24,
    "count": 24,
    "sort": 1,
    "order": "ASC",
    "data": [
        {
            "User.name": "asalas",
            "User.id": 221,
            "User.Location.completename": null,
            "User.UserEmail.email": [
                "a.salas@ieee.org"
            ],
            "User.phone": null,
            "User.is_active": 1,
            "User.firstname": "Alexander",
            "User.phone2": "+58 4164332135",
            "User.mobile": "+58 2432386578",
            "User.Group_User.Group.completename": null,
            "User.last_login": "2017-11-02 04:48:54",
            "User.authtype": 1,
            "User.comment": null,
            "User.language": null,
            "User.date_mod": "2017-11-12 14:39:11",
            "User.Profile_User.Profile.name": [
                "Flyve MDM guest users",
                "Flyve MDM guest users"
            ],
            "User.user_dn": null,
            "User.registration_number": null,
            "User.date_sync": null,
            "User.is_deleted_ldap": 0,
            "User.AuthLDAP.name": null,
            "User.AuthMail.name": null,
            "User.realname": "Alexander Salas Bastidas",
            "User.Ticket_User.Ticket.id": 0,
            "User.Ticket.id": 0,
            "User.begin_date": null,
            "User.end_date": null,
            "User.Entity.name": "Root entity",
            "User.Profile.name": null,
            "User.Profile_User.Entity.completename": [
                "Root entity > asalas@teclib.com",
                "Root entity > asalas@teclib.com"
            ],
            "User.UserTitle.name": null,
            "User.UserCategory.name": null,
            "User.Location.building": null,
            "User.Location.room": null,
            "User.Location.comment": null,
            "User.date_creation": "2017-11-02 04:45:01",
            "User.Link_Itemtype.Link._virtual": null,
            "User.picture": "profile/221_5a084effc6624.jpg"
        },
        {
            "User.name": "jperez",
            "User.id": 187,
            "User.Location.completename": null,
            "User.UserEmail.email": [
                "jperez@teclib.com"
            ],
            "User.phone": null,
            "User.is_active": 1,
            "User.firstname": null,
            "User.phone2": "+58 4164332135",
            "User.mobile": "+58 2432386578",
            "User.Group_User.Group.completename": null,
            "User.last_login": null,
            "User.authtype": 0,
            "User.comment": null,
            "User.language": null,
            "User.date_mod": "2017-10-10 16:21:11",
            "User.Profile_User.Profile.name": "Self-Service",
            "User.user_dn": null,
            "User.registration_number": null,
            "User.date_sync": null,
            "User.is_deleted_ldap": 0,
            "User.AuthLDAP.name": null,
            "User.AuthMail.name": null,
            "User.realname": "John Perez",
            "User.Ticket_User.Ticket.id": 0,
            "User.Ticket.id": 0,
            "User.begin_date": null,
            "User.end_date": null,
            "User.Entity.name": "asalas@teclib.com",
            "User.Profile.name": null,
            "User.Profile_User.Entity.completename": "Root entity > asalas@teclib.com",
            "User.UserTitle.name": null,
            "User.UserCategory.name": null,
            "User.Location.building": null,
            "User.Location.room": null,
            "User.Location.comment": null,
            "User.date_creation": "2017-10-10 16:21:11",
            "User.Link_Itemtype.Link._virtual": null,
            "User.picture": null
        },
        {
            "User.name": "doropeza",
            "User.id": 184,
            "User.Location.completename": null,
            "User.UserEmail.email": [
                "doropeza@teclib.com"
            ],
            "User.phone": null,
            "User.is_active": 1,
            "User.firstname": null,
            "User.phone2": "+58 4164332135",
            "User.mobile": "+58 2432386578",
            "User.Group_User.Group.completename": null,
            "User.last_login": null,
            "User.authtype": 0,
            "User.comment": null,
            "User.language": null,
            "User.date_mod": "2017-10-10 16:19:03",
            "User.Profile_User.Profile.name": "Self-Service",
            "User.user_dn": null,
            "User.registration_number": null,
            "User.date_sync": null,
            "User.is_deleted_ldap": 0,
            "User.AuthLDAP.name": null,
            "User.AuthMail.name": null,
            "User.realname": "Domingo Oropeza",
            "User.Ticket_User.Ticket.id": 0,
            "User.Ticket.id": 0,
            "User.begin_date": null,
            "User.end_date": null,
            "User.Entity.name": "asalas@teclib.com",
            "User.Profile.name": null,
            "User.Profile_User.Entity.completename": "Root entity > asalas@teclib.com",
            "User.UserTitle.name": null,
            "User.UserCategory.name": null,
            "User.Location.building": null,
            "User.Location.room": null,
            "User.Location.comment": null,
            "User.date_creation": "2017-10-10 16:19:03",
            "User.Link_Itemtype.Link._virtual": null,
            "User.picture": "profile/222_5a084effc6624.jpg"
        },
        {
            "User.name": "gmanganiello",
            "User.id": 186,
            "User.Location.completename": null,
            "User.UserEmail.email": [
                "gmanganiello@teclib.com"
            ],
            "User.phone": null,
            "User.is_active": 1,
            "User.firstname": null,
            "User.phone2": "+58 4164332135",
            "User.mobile": "+58 2432386578",
            "User.Group_User.Group.completename": null,
            "User.last_login": null,
            "User.authtype": 0,
            "User.comment": null,
            "User.language": null,
            "User.date_mod": "2017-10-10 16:19:07",
            "User.Profile_User.Profile.name": "Self-Service",
            "User.user_dn": null,
            "User.registration_number": null,
            "User.date_sync": null,
            "User.is_deleted_ldap": 0,
            "User.AuthLDAP.name": null,
            "User.AuthMail.name": null,
            "User.realname": "Gian Franco Manganiello",
            "User.Ticket_User.Ticket.id": 0,
            "User.Ticket.id": 0,
            "User.begin_date": null,
            "User.end_date": null,
            "User.Entity.name": "asalas@teclib.com",
            "User.Profile.name": null,
            "User.Profile_User.Entity.completename": "Root entity > asalas@teclib.com",
            "User.UserTitle.name": null,
            "User.UserCategory.name": null,
            "User.Location.building": null,
            "User.Location.room": null,
            "User.Location.comment": null,
            "User.date_creation": "2017-10-10 16:19:07",
            "User.Link_Itemtype.Link._virtual": null,
            "User.picture": "profile/223_5a084effc6624.jpg"
        },
        {
            "User.name": "glpi",
            "User.id": 2,
            "User.Location.completename": null,
            "User.UserEmail.email": [
                "glpi@teclib.com"
            ],
            "User.phone": "",
            "User.is_active": 1,
            "User.firstname": null,
            "User.phone2": "+58 4164332135",
            "User.mobile": "+58 2432386578",
            "User.Group_User.Group.completename": null,
            "User.last_login": "2017-11-12 14:37:13",
            "User.authtype": 1,
            "User.comment": null,
            "User.language": null,
            "User.date_mod": "2017-11-12 14:38:17",
            "User.Profile_User.Profile.name": "Super-Admin",
            "User.user_dn": null,
            "User.registration_number": null,
            "User.date_sync": null,
            "User.is_deleted_ldap": 0,
            "User.AuthLDAP.name": null,
            "User.AuthMail.name": null,
            "User.realname": "Glpi User",
            "User.Ticket_User.Ticket.id": 0,
            "User.Ticket.id": 0,
            "User.begin_date": null,
            "User.end_date": null,
            "User.Entity.name": "Root entity",
            "User.Profile.name": null,
            "User.Profile_User.Entity.completename": "Root entity",
            "User.UserTitle.name": null,
            "User.UserCategory.name": null,
            "User.Location.building": null,
            "User.Location.room": null,
            "User.Location.comment": null,
            "User.date_creation": null,
            "User.Link_Itemtype.Link._virtual": null,
            "User.picture": "profile/2_5a084ec9dd7ef.png"
        },
        {
            "User.name": "hrondon",
            "User.id": 24,
            "User.Location.completename": null,
            "User.UserEmail.email": [
                "hrondon@teclib.com"
            ],
            "User.phone": "",
            "User.is_active": 1,
            "User.firstname": "Rondon",
            "User.phone2": "+58 4164332135",
            "User.mobile": "+58 2432386578",
            "User.Group_User.Group.completename": null,
            "User.last_login": "2017-11-12 03:46:30",
            "User.authtype": 1,
            "User.comment": "",
            "User.language": null,
            "User.date_mod": "2017-10-25 23:29:45",
            "User.Profile_User.Profile.name": "Super-Admin",
            "User.user_dn": null,
            "User.registration_number": "",
            "User.date_sync": null,
            "User.is_deleted_ldap": 0,
            "User.AuthLDAP.name": null,
            "User.AuthMail.name": null,
            "User.realname": "Hector Rondon",
            "User.Ticket_User.Ticket.id": 0,
            "User.Ticket.id": 0,
            "User.begin_date": null,
            "User.end_date": null,
            "User.Entity.name": "Root entity",
            "User.Profile.name": null,
            "User.Profile_User.Entity.completename": "Root entity",
            "User.UserTitle.name": null,
            "User.UserCategory.name": null,
            "User.Location.building": null,
            "User.Location.room": null,
            "User.Location.comment": null,
            "User.date_creation": "2017-06-23 14:35:29",
            "User.Link_Itemtype.Link._virtual": null,
            "User.picture": "profile/224_5a084effc6624.jpg"
        },
        {
            "User.name": "juperez",
            "User.id": 185,
            "User.Location.completename": null,
            "User.UserEmail.email": [
                "juperez@teclib.com"
            ],
            "User.phone": null,
            "User.is_active": 1,
            "User.firstname": null,
            "User.phone2": "+58 4164332135",
            "User.mobile": "+58 2432386578",
            "User.Group_User.Group.completename": null,
            "User.last_login": null,
            "User.authtype": 0,
            "User.comment": null,
            "User.language": null,
            "User.date_mod": "2017-10-10 16:19:06",
            "User.Profile_User.Profile.name": "Self-Service",
            "User.user_dn": null,
            "User.registration_number": null,
            "User.date_sync": null,
            "User.is_deleted_ldap": 0,
            "User.AuthLDAP.name": null,
            "User.AuthMail.name": null,
            "User.realname": "Juanito Perez",
            "User.Ticket_User.Ticket.id": 0,
            "User.Ticket.id": 0,
            "User.begin_date": null,
            "User.end_date": null,
            "User.Entity.name": "asalas@teclib.com",
            "User.Profile.name": null,
            "User.Profile_User.Entity.completename": "Root entity > asalas@teclib.com",
            "User.UserTitle.name": null,
            "User.UserCategory.name": null,
            "User.Location.building": null,
            "User.Location.room": null,
            "User.Location.comment": null,
            "User.date_creation": "2017-10-10 16:19:06",
            "User.Link_Itemtype.Link._virtual": null,
            "User.picture": null
        },
        {
            "User.name": "nmedina",
            "User.id": 28,
            "User.Location.completename": null,
            "User.UserEmail.email": [
                "nmedina@teclib.com"
            ],
            "User.phone": null,
            "User.is_active": 1,
            "User.firstname": null,
            "User.phone2": "+58 4164332135",
            "User.mobile": "+58 2432386578",
            "User.Group_User.Group.completename": null,
            "User.last_login": null,
            "User.authtype": 1,
            "User.comment": null,
            "User.language": null,
            "User.date_mod": "2017-06-27 21:22:40",
            "User.Profile_User.Profile.name": "Flyve MDM guest users",
            "User.user_dn": null,
            "User.registration_number": null,
            "User.date_sync": null,
            "User.is_deleted_ldap": 0,
            "User.AuthLDAP.name": null,
            "User.AuthMail.name": null,
            "User.realname": "Naylin Medina",
            "User.Ticket_User.Ticket.id": 0,
            "User.Ticket.id": 0,
            "User.begin_date": null,
            "User.end_date": null,
            "User.Entity.name": "Root entity",
            "User.Profile.name": null,
            "User.Profile_User.Entity.completename": "Root entity > asalas@teclib.com",
            "User.UserTitle.name": null,
            "User.UserCategory.name": null,
            "User.Location.building": null,
            "User.Location.room": null,
            "User.Location.comment": null,
            "User.date_creation": "2017-06-27 21:22:40",
            "User.Link_Itemtype.Link._virtual": null,
            "User.picture": "profile/227_5a084effc6624.jpg"
        },
        {
            "User.name": "post-only",
            "User.id": 3,
            "User.Location.completename": null,
            "User.UserEmail.email": [
                "postbot@teclib.com"
            ],
            "User.phone": "",
            "User.is_active": 0,
            "User.firstname": null,
            "User.phone2": "+58 4164332135",
            "User.mobile": "+58 2432386578",
            "User.Group_User.Group.completename": null,
            "User.last_login": null,
            "User.authtype": 0,
            "User.comment": null,
            "User.language": null,
            "User.date_mod": "2017-05-02 17:06:06",
            "User.Profile_User.Profile.name": "Self-Service",
            "User.user_dn": null,
            "User.registration_number": null,
            "User.date_sync": null,
            "User.is_deleted_ldap": 0,
            "User.AuthLDAP.name": null,
            "User.AuthMail.name": null,
            "User.realname": "Post Bot",
            "User.Ticket_User.Ticket.id": 0,
            "User.Ticket.id": 0,
            "User.begin_date": null,
            "User.end_date": null,
            "User.Entity.name": "Root entity",
            "User.Profile.name": null,
            "User.Profile_User.Entity.completename": "Root entity",
            "User.UserTitle.name": null,
            "User.UserCategory.name": null,
            "User.Location.building": null,
            "User.Location.room": null,
            "User.Location.comment": null,
            "User.date_creation": null,
            "User.Link_Itemtype.Link._virtual": null,
            "User.picture": null
        },
        {
            "User.name": "rhernandez",
            "User.id": 23,
            "User.Location.completename": null,
            "User.UserEmail.email": [
                "rhernandez@teclib.com"
            ],
            "User.phone": "",
            "User.is_active": 1,
            "User.firstname": "",
            "User.phone2": "+58 4164332135",
            "User.mobile": "+58 2432386578",
            "User.Group_User.Group.completename": null,
            "User.last_login": "2017-11-05 18:22:37",
            "User.authtype": 1,
            "User.comment": "",
            "User.language": null,
            "User.date_mod": "2017-06-23 14:35:39",
            "User.Profile_User.Profile.name": "Super-Admin",
            "User.user_dn": null,
            "User.registration_number": "",
            "User.date_sync": null,
            "User.is_deleted_ldap": 0,
            "User.AuthLDAP.name": null,
            "User.AuthMail.name": null,
            "User.realname": "Rafael Hernandez",
            "User.Ticket_User.Ticket.id": 0,
            "User.Ticket.id": 0,
            "User.begin_date": null,
            "User.end_date": null,
            "User.Entity.name": "Root entity",
            "User.Profile.name": null,
            "User.Profile_User.Entity.completename": "Root entity",
            "User.UserTitle.name": null,
            "User.UserCategory.name": null,
            "User.Location.building": null,
            "User.Location.room": null,
            "User.Location.comment": null,
            "User.date_creation": "2017-06-23 14:33:09",
            "User.Link_Itemtype.Link._virtual": null,
            "User.picture": "profile/225_5a084effc6624.jpg"
        },
        {
            "User.name": "tech",
            "User.id": 4,
            "User.Location.completename": null,
            "User.UserEmail.email": [
                "tech@teclib.com"
            ],
            "User.phone": "",
            "User.is_active": 0,
            "User.firstname": null,
            "User.phone2": "+58 4164332135",
            "User.mobile": "+58 2432386578",
            "User.Group_User.Group.completename": null,
            "User.last_login": "2017-05-02 17:06:14",
            "User.authtype": 1,
            "User.comment": null,
            "User.language": null,
            "User.date_mod": "2017-05-02 17:06:14",
            "User.Profile_User.Profile.name": "Technician",
            "User.user_dn": null,
            "User.registration_number": null,
            "User.date_sync": null,
            "User.is_deleted_ldap": 0,
            "User.AuthLDAP.name": null,
            "User.AuthMail.name": null,
            "User.realname": "Tech Bot",
            "User.Ticket_User.Ticket.id": 0,
            "User.Ticket.id": 0,
            "User.begin_date": null,
            "User.end_date": null,
            "User.Entity.name": "Root entity",
            "User.Profile.name": null,
            "User.Profile_User.Entity.completename": "Root entity",
            "User.UserTitle.name": null,
            "User.UserCategory.name": null,
            "User.Location.building": null,
            "User.Location.room": null,
            "User.Location.comment": null,
            "User.date_creation": null,
            "User.Link_Itemtype.Link._virtual": null,
            "User.picture": null
        },
        {
            "User.name": "tbugier",
            "User.id": 4,
            "User.Location.completename": null,
            "User.UserEmail.email": [
                "tbugier@teclib.com"
            ],
            "User.phone": "",
            "User.is_active": 0,
            "User.firstname": null,
            "User.phone2": "+58 4164332135",
            "User.mobile": "+58 2432386578",
            "User.Group_User.Group.completename": null,
            "User.last_login": "2017-05-02 17:06:14",
            "User.authtype": 1,
            "User.comment": null,
            "User.language": null,
            "User.date_mod": "2017-05-02 17:06:14",
            "User.Profile_User.Profile.name": "Technician",
            "User.user_dn": null,
            "User.registration_number": null,
            "User.date_sync": null,
            "User.is_deleted_ldap": 0,
            "User.AuthLDAP.name": null,
            "User.AuthMail.name": null,
            "User.realname": "Thierry Bugier",
            "User.Ticket_User.Ticket.id": 0,
            "User.Ticket.id": 0,
            "User.begin_date": null,
            "User.end_date": null,
            "User.Entity.name": "Root entity",
            "User.Profile.name": null,
            "User.Profile_User.Entity.completename": "Root entity",
            "User.UserTitle.name": null,
            "User.UserCategory.name": null,
            "User.Location.building": null,
            "User.Location.room": null,
            "User.Location.comment": null,
            "User.date_creation": null,
            "User.Link_Itemtype.Link._virtual": null,
            "User.picture": "profile/226_5a084effc6624.jpg"
        }
    ],
    "content-range": "0-23/24"
}